fastembed/__init__.py
fastembed/common/__init__.py
fastembed/common/model_management.py
fastembed/common/onnx_model.py
fastembed/common/preprocessor_utils.py
fastembed/common/types.py
fastembed/common/utils.py
fastembed/embedding.py
fastembed/image/__init__.py
fastembed/image/image_embedding.py
fastembed/image/image_embedding_base.py
fastembed/image/onnx_embedding.py
fastembed/image/onnx_image_model.py
fastembed/image/transform/functional.py
fastembed/image/transform/operators.py
fastembed/late_interaction/__init__.py
fastembed/late_interaction/colbert.py
fastembed/late_interaction/late_interaction_embedding_base.py
fastembed/late_interaction/late_interaction_text_embedding.py
fastembed/parallel_processor.py
fastembed/sparse/__init__.py
fastembed/sparse/bm25.py
fastembed/sparse/bm42.py
fastembed/sparse/sparse_embedding_base.py
fastembed/sparse/sparse_text_embedding.py
fastembed/sparse/splade_pp.py
fastembed/sparse/utils/tokenizer.py
fastembed/text/__init__.py
fastembed/text/clip_embedding.py
fastembed/text/e5_onnx_embedding.py
fastembed/text/onnx_embedding.py
fastembed/text/onnx_text_model.py
fastembed/text/pooled_embedding.py
fastembed/text/pooled_normalized_embedding.py
fastembed/text/text_embedding.py
fastembed/text/text_embedding_base.py
fastembed-0.3.5.dist-info/LICENSE
fastembed-0.3.5.dist-info/METADATA
fastembed-0.3.5.dist-info/WHEEL
fastembed-0.3.5.dist-info/RECORD
