Metadata-Version: 2.1
Name: fastembed
Version: 0.3.5
Summary: Fast, light, accurate library built for retrieval embedding generation
Home-page: https://github.com/qdrant/fastembed
License: Apache License
Keywords: vector,embedding,neural,search,qdrant,sentence-transformers
Author: Qdrant Team
Author-email: info@qdrant.tech
Requires-Python: >=3.8.0,<3.13
Classifier: License :: Other/Proprietary License
Classifier: Programming Language :: Python :: 3
Classifier: Programming Language :: Python :: 3.8
Classifier: Programming Language :: Python :: 3.9
Classifier: Programming Language :: Python :: 3.10
Classifier: Programming Language :: Python :: 3.11
Classifier: Programming Language :: Python :: 3.12
Requires-Dist: PyStemmer (>=2.2.0,<3.0.0)
Requires-Dist: huggingface-hub (>=0.20,<1.0)
Requires-Dist: loguru (>=0.7.2,<0.8.0)
Requires-Dist: mmh3 (>=4.0,<5.0)
Requires-Dist: numpy (>=1.21,<2) ; python_version < "3.12"
Requires-Dist: numpy (>=1.26,<2) ; python_version >= "3.12"
Requires-Dist: onnx (>=1.15.0,<2.0.0)
Requires-Dist: onnxruntime (>=1.17.0,<2.0.0)
Requires-Dist: pillow (>=10.3.0,<11.0.0)
Requires-Dist: requests (>=2.31,<3.0)
Requires-Dist: snowballstemmer (>=2.2.0,<3.0.0)
Requires-Dist: tokenizers (>=0.15,<1.0)
Requires-Dist: tqdm (>=4.66,<5.0)
Project-URL: Repository, https://github.com/qdrant/fastembed
